JosLab/README.md
JosLab/__init__.py
JosLab/__main__.py
JosLab/file.epub
JosLab/index.html
JosLab/css/__init__.py
JosLab/css/annotations.css
JosLab/css/main.css
JosLab/css/normalize.css
JosLab/css/popup.css
JosLab/font/__init__.py
JosLab/font/fontello.eot
JosLab/font/fontello.svg
JosLab/font/fontello.ttf
JosLab/font/fontello.woff
JosLab/img/__init__.py
JosLab/img/annotator-glyph-sprite.png
JosLab/img/annotator-icon-sprite.png
JosLab/img/apple-touch-icon.png
JosLab/img/cancelfullscreen.png
JosLab/img/close.png
JosLab/img/fullscreen.png
JosLab/img/loader.gif
JosLab/img/menu-icon.png
JosLab/img/save.png
JosLab/img/saved.png
JosLab/img/settings-s.png
JosLab/img/settings.png
JosLab/img/star.png
JosLab/js/__init__.py
JosLab/js/epub.js
JosLab/js/epub.min.js
JosLab/js/epub.min.map
JosLab/js/hooks.min.js
JosLab/js/hooks.min.map
JosLab/js/reader.js
JosLab/js/reader.js.map
JosLab/js/reader.min.js
JosLab/js/reader.min.map
JosLab/js/hooks/__init__.py
JosLab/js/hooks/extensions/__init__.py
JosLab/js/hooks/extensions/highlight.js
JosLab/js/libs/__init__.py
JosLab/js/libs/jquery.min.js
JosLab/js/libs/localforage.min.js
JosLab/js/libs/screenfull.js
JosLab/js/libs/screenfull.min.js
JosLab/js/libs/zip.min.js
JosLab/js/plugins/__init__.py
JosLab/js/plugins/hypothesis.js
JosLab/js/plugins/search.js
jos_lab-2024.3.2.0.dist-info/METADATA
jos_lab-2024.3.2.0.dist-info/WHEEL
jos_lab-2024.3.2.0.dist-info/entry_points.txt
jos_lab-2024.3.2.0.dist-info/top_level.txt
jos_lab-2024.3.2.0.dist-info/RECORD
